ida_statusbar/__init__.py
ida_statusbar/statusbar.py
ida_statusbar/utils.py
ida_statusbar-0.1.0.dist-info/METADATA
ida_statusbar-0.1.0.dist-info/WHEEL
ida_statusbar-0.1.0.dist-info/top_level.txt
ida_statusbar-0.1.0.dist-info/RECORD
