Metadata-Version: 2.1
Name: ida-statusbar
Version: 0.1.0
Summary: Support custom status bar for IDA
Requires-Python: >=3.8
